tnfsh_wiki_teachers_core/__init__.py
tnfsh_wiki_teachers_core/abc/__init__.py
tnfsh_wiki_teachers_core/abc/cache_abc.py
tnfsh_wiki_teachers_core/abc/crawler_abc.py
tnfsh_wiki_teachers_core/abc/domain_abc.py
tnfsh_wiki_teachers_core/index/__init__.py
tnfsh_wiki_teachers_core/index/cache.py
tnfsh_wiki_teachers_core/index/crawler.py
tnfsh_wiki_teachers_core/index/index.py
tnfsh_wiki_teachers_core/utils/__init__.py
tnfsh_wiki_teachers_core/utils/dict_root_model.py
tnfsh_wiki_teachers_core/utils/logger.py
tnfsh_wiki_teachers_core-1.0.0.dist-info/licenses/LICENSE
tnfsh_wiki_teachers_core-1.0.0.dist-info/METADATA
tnfsh_wiki_teachers_core-1.0.0.dist-info/WHEEL
tnfsh_wiki_teachers_core-1.0.0.dist-info/top_level.txt
tnfsh_wiki_teachers_core-1.0.0.dist-info/RECORD
