Metadata-Version: 2.4
Name: tnfsh-wiki-teachers-core
Version: 1.0.0
Summary: 竹園wiki教師資料核心功能庫，竹園wiki為台南一中wiki
Author-email: Skywind5487 <skywind5487@example.com>
License-Expression: MIT
Project-URL: Source, https://github.com/weiting/tnfsh-wiki-teachers-core
Keywords: teacher,education,management
Classifier: Development Status :: 3 - Alpha
Classifier: Intended Audience :: Education
Classifier: Programming Language :: Python :: 3
Classifier: Programming Language :: Python :: 3.8
Classifier: Programming Language :: Python :: 3.9
Classifier: Programming Language :: Python :: 3.10
Classifier: Programming Language :: Python :: 3.11
Classifier: Programming Language :: Python :: 3.12
Requires-Python: >=3.8
License-File: LICENSE
Requires-Dist: aiohttp>=3.10.11
Requires-Dist: dotenv>=0.9.9
Requires-Dist: pydantic>=2.10.6
Dynamic: license-file
